obsidian_admonitions/__init__.py
obsidian_admonitions/extension.py
obsidian_to_material-0.1.2.dist-info/licenses/LICENSE
obsidian_to_material-0.1.2.dist-info/METADATA
obsidian_to_material-0.1.2.dist-info/WHEEL
obsidian_to_material-0.1.2.dist-info/entry_points.txt
obsidian_to_material-0.1.2.dist-info/top_level.txt
obsidian_to_material-0.1.2.dist-info/RECORD
