Metadata-Version: 2.4
Name: obsidian-to-material
Version: 0.1.2
Summary: Transform Obsidian-style admonitions into MkDocs Material admonitions automatically.
Author-email: Ángel Bonet <angel.bonet@gmail.com>
License: MIT
Classifier: Programming Language :: Python :: 3
Classifier: License :: OSI Approved :: MIT License
Requires-Python: >=3.12
License-File: LICENSE
Dynamic: license-file
